{
  "huajian": {
    "name": "花间游",
    "nickname": ["花间", "花间游", "草里爬"]
  },
  "lijing": {
    "name": "离经易道",
    "nickname": ["奶花", "离经易道", "离经", "花奶"]
  },
  "binxin": {
    "name": "冰心诀",
    "nickname": ["冰心", "冰心诀", "冰心决"]
  },
  "yunchang": {
    "name": "云裳心经",
    "nickname": ["奶秀", "云裳心经", "云裳", "秀奶"]
  },
  "yijin": {
    "name": "易筋经",
    "nickname": ["和尚", "易筋经", "易筋", "秃子", "光头", "灯泡", "秃驴"]
  },
  "xisui": {
    "name": "洗髓经",
    "nickname": ["和尚T", "洗髓经", "洗髓", "秃T", "圣僧", "佛祖"]
  },
  "zixia": {
    "name": "紫霞功",
    "nickname": ["气纯", "紫霞功", "紫霞"]
  },
  "taixu": {
    "name": "太虚剑意",
    "nickname": ["剑纯", "太虚剑意", "备胎"]
  },
  "aoxue": {
    "name": "傲血战意",
    "nickname": ["天策", "傲血战意", "傲血", "哈士奇", "狗子", "二哈"]
  },
  "tielao": {
    "name": "铁牢律",
    "nickname": ["策T", "铁牢律", "铁牢", "天策T"]
  },
  "wenshui": {
    "name": "问水诀",
    "nickname": ["藏剑", "问水诀", "问水", "问水决", "黄鸡", "叽", "黄叽", "KFC", "kfc", "星期四"]
  },
  "dujing": {
    "name": "毒经",
    "nickname": ["毒经", "五毒"]
  },
  "butian": {
    "name": "补天诀",
    "nickname": ["奶毒", "补天诀", "补天", "毒奶"]
  },
  "jingyu": {
    "name": "惊羽诀",
    "nickname": ["鲸鱼", "惊羽诀", "惊羽", "惊羽决"]
  },
  "tianluo": {
    "name": "天罗诡道",
    "nickname": ["田螺", "天罗诡道", "天罗"]
  },
  "fenying": {
    "name": "焚影圣诀",
    "nickname": ["焚影", "焚影圣诀", "喵", "喵喵", "明教"]
  },
  "mingzun": {
    "name": "明尊琉璃体",
    "nickname": ["喵T", "明尊琉璃体", "明尊", "明教T"]
  },
  "xiaochen": {
    "name": "笑尘诀",
    "nickname": ["丐帮", "笑尘诀", "帅比", "无敌心法", "最强心法"]
  },
  "fenshan": {
    "name": "分山劲",
    "nickname": ["苍云", "分山劲", "分山", "岔劲", "乌龟", "龟龟", "盾盾"]
  },
  "tiegu": {
    "name": "铁骨衣",
    "nickname": ["苍云T", "铁骨衣", "铁骨"]
  },
  "mowen": {
    "name": "莫问",
    "nickname": ["莫问", "长歌", "鸽子", "咕咕"]
  },
  "xiangzhi": {
    "name": "相知",
    "nickname": ["奶歌", "相知", "歌奶", "奶鸽", "鸽奶", "奶咕", "咕奶"]
  },
  "beiao": {
    "name": "北傲诀",
    "nickname": ["霸刀", "北傲诀", "貂貂"]
  },
  "linghai": {
    "name": "凌海诀",
    "nickname": ["蓬莱", "凌海诀", "凌海决", "伞"]
  },
  "yinlong": {
    "name": "隐龙诀",
    "nickname": ["凌雪", "隐龙诀", "隐龙决", "凌雪阁"]
  },
  "taixuan": {
    "name": "太玄经",
    "nickname": ["衍天", "太玄经", "衍天宗", "灯灯", "算卦的"]
  },
  "wufang": {
    "name": "无方",
    "nickname": ["无方", "药宗", "药药"]
  },
  "lingsu": {
    "name": "灵素",
    "nickname": ["药奶", "灵素", "奶药"]
  },
  "gufeng": {
    "name": "孤峰诀",
    "nickname": ["刀宗", "孤峰诀", "孤峰决"]
  },
  "shanhai": {
    "name": "山海心诀",
    "nickname": ["万灵", "山海心诀", "弓"]
  },
  "zhoutian": {
    "name": "周天功",
    "nickname": ["段氏", "周天功", "扇子", "扇"]
  }
}
